{
    "name": "power.proviorigins.jellysculk.no_game_events.name",
    "description": "power.proviorigins.jellysculk.no_game_events.desc",
    "type": "origins:multiple",

    "prevent_most": {
        "type": "origins:prevent_game_event",
        "events": [
            "minecraft:step",
            "minecraft:swim",
            "minecraft:hit_ground",
            "minecraft:block_change",
            "minecraft:splash",
            "minecraft:projectile_shoot",
            "minecraft:eat",
            "minecraft:equip",
            "minecraft:shear",
            "minecraft:entity_place",
            "minecraft:fluid_place",
            "minecraft:block_destroy",
            "minecraft:fluid_pickup",
            "minecraft:container_close",
            "minecraft:container_open"
        ]
    },

    "occulude": {
        "type": "proviorigins:occlude_vibrations"
    }
}