{
    "powers": [
        "proviorigins:jellysculk/entity_detect",
        "proviorigins:jellysculk/scoreboard_manager",
        "proviorigins:common/no_game_events",
        "proviorigins:jellysculk/spread_sculk",
        "proviorigins:jellysculk/create_sensor",
        "proviorigins:jellysculk/break_sculk_fast",
        "proviorigins:common/double_jump",
        "proviorigins:common/slow_fall",
        "origins:fall_immunity",
        "proviorigins:jellysculk/buffs_on_sculk",
        "proviorigins:jellysculk/debuffs_off_sculk",
        "proviorigins:common/brittle",
        "extrade:fungifloral"
    ],
    "icon": "proviorigins:jelly",
    "impact": 3,
    "name": "power.proviorigins.jellysculk.name",
    "description": "power.proviorigins.jellysculk.description"
}